PyTaskScheduler-0.0.1.2.data/scripts/ts
ts/DAG.py
ts/__init__.py
ts/__main__.py
ts/project.py
ts/utility.py
ts/UI/CLI.py
ts/UI/__init__.py
ts/UI/task_builder.py
ts/tasks/__init__.py
ts/tasks/tasks.py
PyTaskScheduler-0.0.1.2.dist-info/LICENSE
PyTaskScheduler-0.0.1.2.dist-info/METADATA
PyTaskScheduler-0.0.1.2.dist-info/WHEEL
PyTaskScheduler-0.0.1.2.dist-info/top_level.txt
PyTaskScheduler-0.0.1.2.dist-info/RECORD
