Metadata-Version: 2.1
Name: PyTaskScheduler
Version: 0.0.1.2
Summary: This package focus on build a task scheduler via Python. With TaskScheduler you can define a project with tasks which have some dependency on each other, and run this project.
Home-page: https://github.com/lizeyan/TaskScheduler
Author: Zeyan Li
Author-email: li_zeyan@icloud.com
License: MIT
Project-URL: Bug Tracker, https://github.com/lizeyan/TaskScheduler/issues
Project-URL: Source Code, https://github.com/lizeyan/TaskScheduler
Project-URL: Documentation, https://ts.lizeyan.me
Platform: UNKNOWN
Classifier: Programming Language :: Python :: 3
Classifier: License :: OSI Approved :: MIT License
Classifier: Operating System :: OS Independent
Requires-Python: >=3.6
Requires-Dist: Click (~=7.1.2)
Requires-Dist: loguru (~=0.4.1)
Requires-Dist: ordered-set (~=4.0.1)
Requires-Dist: Jinja2 (~=2.11.2)
